setup.py
invoicing_sunsetriders/__init__.py
invoicing_sunsetriders/invoice.py
invoicing_sunsetriders/test.py
invoicing_sunsetriders.egg-info/PKG-INFO
invoicing_sunsetriders.egg-info/SOURCES.txt
invoicing_sunsetriders.egg-info/dependency_links.txt
invoicing_sunsetriders.egg-info/requires.txt
invoicing_sunsetriders.egg-info/top_level.txt